payloadcomputerdroneprojekt/__init__.py
payloadcomputerdroneprojekt/helper.py
payloadcomputerdroneprojekt/camera/__init__.py
payloadcomputerdroneprojekt/camera/abstract_class.py
payloadcomputerdroneprojekt/camera/raspi2.py
payloadcomputerdroneprojekt/camera/gazebo_sitl/__init__.py
payloadcomputerdroneprojekt/camera/gazebo_sitl/gazebo_cam.py
payloadcomputerdroneprojekt/camera/gazebo_sitl/gazebo_camera_lib.py
payloadcomputerdroneprojekt/communications/__init__.py
payloadcomputerdroneprojekt/communications/comm_class.py
payloadcomputerdroneprojekt/communications/helper.py
payloadcomputerdroneprojekt/image_analysis/__init__.py
payloadcomputerdroneprojekt/image_analysis/data_handler.py
payloadcomputerdroneprojekt/image_analysis/data_item.py
payloadcomputerdroneprojekt/image_analysis/ia_class.py
payloadcomputerdroneprojekt/image_analysis/math_helper.py
payloadcomputerdroneprojekt/mission_computer/__init__.py
payloadcomputerdroneprojekt/mission_computer/helper.py
payloadcomputerdroneprojekt/mission_computer/mc_class.py
payloadcomputerdroneprojekt/mission_computer/scan_planer.py
payloadcomputerdroneprojekt/test/__init__.py
payloadcomputerdroneprojekt/test/communications/__init__.py
payloadcomputerdroneprojekt/test/communications/test_SITL_get_data.py
payloadcomputerdroneprojekt/test/communications/test_SITL_mov.py
payloadcomputerdroneprojekt/test/image_analysis/__init__.py
payloadcomputerdroneprojekt/test/image_analysis/config_px4.json
payloadcomputerdroneprojekt/test/image_analysis/helper.py
payloadcomputerdroneprojekt/test/image_analysis/test_code.py
payloadcomputerdroneprojekt/test/image_analysis/test_code2.py
payloadcomputerdroneprojekt/test/image_analysis/test_color.py
payloadcomputerdroneprojekt/test/image_analysis/test_config.json
payloadcomputerdroneprojekt/test/image_analysis/test_config_2.json
payloadcomputerdroneprojekt/test/image_analysis/test_image.py
payloadcomputerdroneprojekt/test/image_analysis/test_pixel_calc.py
payloadcomputerdroneprojekt-1.0.0.dist-info/licenses/LICENSE.txt
payloadcomputerdroneprojekt-1.0.0.dist-info/METADATA
payloadcomputerdroneprojekt-1.0.0.dist-info/WHEEL
payloadcomputerdroneprojekt-1.0.0.dist-info/top_level.txt
payloadcomputerdroneprojekt-1.0.0.dist-info/RECORD
