Metadata-Version: 2.4
Name: PayloadComputerDroneProjekt
Version: 1.0.0
Summary: Add a short description here!
Home-page: https://github.com/KonstantinDege/PayloadComputerDroneProjekt
Author: KonstantinDege
Author-email: 150815971+KonstantinDege@users.noreply.github.com
License: MIT
Project-URL: Documentation, https://konstantindege.github.io/PayloadComputerDroneProjekt/
Platform: any
Classifier: Development Status :: 4 - Beta
Classifier: Programming Language :: Python
License-File: LICENSE.txt
Requires-Dist: importlib-metadata; python_version < "3.8"
Requires-Dist: mavsdk<4.0.0,>=1.0.0
Requires-Dist: opencv-python<5.0.0,>=4.5.0
Requires-Dist: numpy<3.0,>=1.22
Requires-Dist: scipy<2.0,>=1.8
Requires-Dist: pyproj<4.0,>=3.3
Requires-Dist: python-multipart<1.0,>=0.0.5
Requires-Dist: fastapi<1.0,>=0.95
Requires-Dist: uvicorn<1.0,>=0.20
Requires-Dist: shapely<3.0,>=2.0
Provides-Extra: testing
Requires-Dist: setuptools; extra == "testing"
Requires-Dist: pytest; extra == "testing"
Requires-Dist: pytest-cov; extra == "testing"
Requires-Dist: libgz-transport13; extra == "testing"
Dynamic: license-file
